xml_to_pandas/__init__.py
xml_to_pandas/xml_to_pandas.py
xml_to_pandas-0.3.dist-info/LICENSE
xml_to_pandas-0.3.dist-info/METADATA
xml_to_pandas-0.3.dist-info/WHEEL
xml_to_pandas-0.3.dist-info/top_level.txt
xml_to_pandas-0.3.dist-info/RECORD
