Metadata-Version: 2.1
Name: xml_to_pandas
Version: 0.3
Summary: Converts all kinds of XML files to a pandas dataframe
Author: Pinak Tendulkar
Author-email: pdtendulkar140203@gmail.com.com
License: MIT
Project-URL: Source Repository, https://github.com/Pi2003/
License-File: LICENSE
Requires-Dist: pandas
